<module>
  2           0 LOAD_CONST               0 (<code object <module> at 0x0000028E5C631390, file "<string>", line 1>)
              2 LOAD_CONST               1 ('f')
              4 MAKE_FUNCTION            0
              6 STORE_GLOBAL             0 (f)

  4           8 LOAD_GLOBAL              1 (print)
             10 LOAD_GLOBAL              2 (to_t)
             12 LOAD_GLOBAL              3 (get_event_loop)
             14 CALL_FUNCTION            0
             16 LOAD_ATTR                4 (run_until_complete)
             18 LOAD_GLOBAL              0 (f)

  1          20 CALL_FUNCTION            0
             22 CALL_FUNCTION            1
             24 CALL_FUNCTION            1
             26 CALL_FUNCTION            1
             28 POP_TOP
             30 LOAD_CONST               2 (None)
             32 RETURN_VALUE

Disassembly of <code object <module> at 0x0000028E5C631390, file "<string>", line 1>:
  1           0 LOAD_CONST               0 (<code object <module> at 0x0000028E5C1231E0, file "<string>", line 1>)
              2 LOAD_CONST               1 ('<module>.<locals>.<genexp>')
              4 MAKE_FUNCTION            0

  3           6 LOAD_GLOBAL              0 (range)
              8 LOAD_CONST               2 (2)
             10 CALL_FUNCTION            1
             12 GET_ITER
             14 CALL_FUNCTION            1
             16 RETURN_VALUE
             18 LOAD_CONST               3 (None)
             20 RETURN_VALUE

Disassembly of <code object <module> at 0x0000028E5C1231E0, file "<string>", line 1>:
  1           0 LOAD_FAST                0 (.0)
        >>    2 FOR_ITER                56 (to 60)

  3           4 STORE_FAST               1 (k)
              6 LOAD_GLOBAL              0 (S)
              8 CALL_FUNCTION            0
        >>   10 GET_AITER
             12 SETUP_EXCEPT            12 (to 26)
             14 GET_ANEXT
             16 LOAD_CONST               0 (None)
             18 YIELD_FROM
             20 STORE_FAST               2 (i)
             22 POP_BLOCK
             24 JUMP_FORWARD            10 (to 36)
        >>   26 DUP_TOP
             28 LOAD_GLOBAL              1 (StopAsyncIteration)
             30 COMPARE_OP              10 (exception match)
             32 POP_JUMP_IF_TRUE        48
             34 END_FINALLY
        >>   36 LOAD_FAST                2 (i)
             38 LOAD_CONST               1 (5)
             40 BINARY_MODULO
             42 YIELD_VALUE
             44 POP_TOP
             46 JUMP_ABSOLUTE           10
        >>   48 POP_TOP
             50 POP_TOP
             52 POP_TOP
             54 POP_EXCEPT
             56 POP_TOP
             58 JUMP_ABSOLUTE            2
        >>   60 LOAD_CONST               0 (None)
             62 RETURN_VALUE
